dynamicaug/__init__.py
dynamicaug/_functional_pil.py
dynamicaug/_functional_tensor.py
dynamicaug/_utils.py
dynamicaug/functional.py
dynamicaug/transforms.py
dynamicaug-0.0.2.dist-info/LICENSE.txt
dynamicaug-0.0.2.dist-info/METADATA
dynamicaug-0.0.2.dist-info/WHEEL
dynamicaug-0.0.2.dist-info/top_level.txt
dynamicaug-0.0.2.dist-info/RECORD
