Metadata-Version: 2.1
Name: dynamicaug
Version: 0.0.2
Summary: pytorch implementation of dynamic augmentation
Home-page: https://github.com/krjeo/DynamicAugmentation
Author: JeonghyunKim
Author-email: kr.jeonghyun.kim@gmail.com
Classifier: Programming Language :: Python :: 3
Classifier: License :: OSI Approved :: MIT License
Classifier: Operating System :: OS Independent
Requires-Python: >=3.9
License-File: LICENSE.txt
